ZabbixService/__init__.py
ZabbixService/__main__.py
ZabbixService/const.py
ZabbixService/service.py
pih_zabbix-0.15.dist-info/METADATA
pih_zabbix-0.15.dist-info/WHEEL
pih_zabbix-0.15.dist-info/entry_points.txt
pih_zabbix-0.15.dist-info/top_level.txt
pih_zabbix-0.15.dist-info/RECORD
