Metadata-Version: 2.1
Name: pih-zabbix
Version: 0.15
Summary: PIH Zabbix service package
Home-page: https://pacifichosp.com/
Author: Nikita Karachentsev
Author-email: it@pacifichosp.com
License: MIT
Requires-Dist: ipih
Requires-Dist: pyzabbix
Requires-Dist: zabbix-utils
